llama_index/packs/llava_completion/__init__.py
llama_index/packs/llava_completion/base.py
llama_index_packs_llava_completion-0.4.1.dist-info/METADATA
llama_index_packs_llava_completion-0.4.1.dist-info/WHEEL
llama_index_packs_llava_completion-0.4.1.dist-info/licenses/LICENSE
llama_index_packs_llava_completion-0.4.1.dist-info/RECORD
