Metadata-Version: 2.4
Name: llama-index-packs-llava-completion
Version: 0.4.1
Summary: llama-index packs llava_completion integration
Author-email: Your Name <you@example.com>
Maintainer: wenqiglantz
License-Expression: MIT
License-File: LICENSE
Keywords: image,llava,multimodal
Requires-Python: <4.0,>=3.9
Requires-Dist: llama-index-core<0.15,>=0.13.0
Requires-Dist: llama-index-llms-replicate<0.6,>=0.5.0
Requires-Dist: replicate<0.24,>=0.23.1
